{
    "ClassID": "bb-imperatritsa-mariya",
    "ClassName": "Imperatritsa Mariya Class",
    "Nation": "rus",

    "Type": "Battleship",
    "SubType": "Dreadnought",
    "Existance": "Built",
    "ClassLaidDown": "1911-10-30",
    "StandardDisplacement": 23413,

    "ShipHorsePower": 26000,
    "Speed": 21,
    "Range": 3037,

    "MainGun": "305/52 Pattern 1907",
    "MainBroadside": 12,
    "SecondaryGun": "130/53 MK-4",
    "SecondaryBroadside": 10,

    "ArmorBelt": 262,
    "ArmorBeltAngle": 0
}