{
    "ClassID": "cds-dristigheten",
    "ClassName": "Dristigheten Class",
    "Nation": "swn",

    "Type": "Coastal Defense",
    "SubType": "Coastal Defense Ship",
    "Existance": "Built",
    "ClassLaidDown": "1898-01-01",
    "StandardDisplacement": 3445,

    "ShipHorsePower": 5400,
    "Speed": 16.5,
    "Range": 3780,

    "MainGun": "209/44 M1898",
    "MainBroadside": 2,
    "SecondaryGun": "152/44 M1898",
    "SecondaryBroadside": 3,

    "ArmorBelt": 203,
    "ArmorBeltAngle": 0
}