{
    "ClassID": "ac-cressy",
    "ClassName": "Cressy Class",
    "Nation": "rn",

    "Type": "Cruiser",
    "SubType": "Armored Cruiser",
    "Existance": "Built",
    "ClassLaidDown": "1898-02-15",
    "StandardDisplacement": 12000,

    "ShipHorsePower": 21000,
    "Speed": 21,
    "Range": 4833,

    "MainGun": "234/47 BL Mark X",
    "MainBroadside": 2,
    "SecondaryGun": "152/45 BL Mark VII",
    "SecondaryBroadside": 6,

    "ArmorBelt": 152,
    "ArmorBeltAngle": 0
}