{
    "ClassID": "ac-warrior",
    "ClassName": "Warrior Class",
    "Nation": "rn",

    "Type": "Cruiser",
    "SubType": "Armored Cruiser",
    "Existance": "Built",
    "ClassLaidDown": "1903-11-05",
    "StandardDisplacement": 13550,

    "ShipHorsePower": 23000,
    "Speed": 23,
    "Range": 10741,

    "MainGun": "234/47 BL Mark X",
    "MainBroadside": 4,
    "SecondaryGun": "190/50 BL Mark II",
    "SecondaryBroadside": 2,

    "ArmorBelt": 152,
    "ArmorBeltAngle": 0
}