{
    "ClassID": "cl-fiji",
    "ClassName": "Fiji Class",
    "Nation": "rn",

    "Type": "Cruiser",
    "SubType": "Light Cruiser",
    "Existance": "Built",
    "ClassLaidDown": "1937-12-01",
    "StandardDisplacement": 8530,

    "ShipHorsePower": 72500,
    "Speed": 31.5,
    "Range": 18000,

    "MainGun": "152/50 BL Mark XXIII",
    "MainBroadside": 12,
    "SecondaryGun": "102/45 QF Mark XVI",
    "SecondaryBroadside": 4,

    "ArmorBelt": 89,
    "ArmorBeltAngle": 0
}