{
    "ClassID": "cl-ying-swei",
    "ClassName": "Ying-swei Class",
    "Nation": "China",

    "Type": "Cruiser",
    "SubType": "Protected Cruiser",
    "Existance": "Built",
    "ClassLaidDown": "1910-03-01",
    "StandardDisplacement": 2460,

    "ShipHorsePower": 6000,
    "Speed": 20,
    "Range": 9260,

    "MainGun": "152/45 Armstrong NN",
    "MainBroadside": 2,
    "SecondaryGun": "102/50 Armstrong P",
    "SecondaryBroadside": 2,

    "ArmorBelt": 0,
    "ArmorBeltAngle": 0,
    "ArmorDeck": 37
}