[
    {
        "ClassID": "bb-Kaiser",
        "ShipName": "SMS Kaiser",
        "Existance": "Built",
        "LaidDown": "1909-10-01",
        "Launched": "1911-03-22",
        "Commissioned": "1912-08-01"
    },
    {
        "ClassID": "bb-Kaiser",
        "ShipName": "SMS Friedrich der Grosse",
        "Existance": "Built",
        "LaidDown": "1910-01-01",
        "Launched": "1911-06-10",
        "Commissioned": "1912-10-15"
    },
    {
        "ClassID": "bb-Kaiser",
        "ShipName": "SMS Kaiserin",
        "Existance": "Built",
        "LaidDown": "1910-11-01",
        "Launched": "1911-11-11",
        "Commissioned": "1913-05-14"
    },
    {
        "ClassID": "bb-Kaiser",
        "ShipName": "SMS Prinzregent Luitpold",
        "Existance": "Built",
        "LaidDown": "1910-10-01",
        "Launched": "1912-02-17",
        "Commissioned": "1913-08-19"
    },
    {
        "ClassID": "bb-Kaiser",
        "ShipName": "SMS Konig Albert",
        "Existance": "Built",
        "LaidDown": "1910-07-01",
        "Launched": "1912-04-27",
        "Commissioned": "1913-07-31"
    }
]